README.rst
setup.py
pydebrid/__init__.py
pydebrid/main.py
pydebrid.egg-info/PKG-INFO
pydebrid.egg-info/SOURCES.txt
pydebrid.egg-info/dependency_links.txt
pydebrid.egg-info/entry_points.txt
pydebrid.egg-info/requires.txt
pydebrid.egg-info/top_level.txt
pydebrid/core/__init__.py
pydebrid/core/alldebrid.py
pydebrid/core/downloader.py
pydebrid/core/pydconfig.py
pydebrid/core/subtitle.py
pydebrid/core/uri.py