Metadata-Version: 1.1
Name: pydebrid
Version: 1.0.2
Summary: A cross-platform Alldebrid CLI with downloader and subtitles finder
Home-page: https://github.com/davidderus/pydebrid
Author: David Dérus
Author-email: UNKNOWN
License: UNKNOWN
Platform: UNKNOWN
Classifier: Programming Language :: Python
Classifier: Environment :: Console
Classifier: Development Status :: 4 - Beta
Classifier: License :: OSI Approved :: Apache Software License
Classifier: Natural Language :: English
Classifier: Operating System :: OS Independent
Classifier: Programming Language :: Python :: 2.7
Classifier: Topic :: Utilities
Classifier: Topic :: Internet
Classifier: Intended Audience :: Other Audience
